termexec/__init__.py
termexec/lib.py
termexec-0.0.3.dist-info/licenses/LICENSE
termexec-0.0.3.dist-info/METADATA
termexec-0.0.3.dist-info/WHEEL
termexec-0.0.3.dist-info/top_level.txt
termexec-0.0.3.dist-info/RECORD
