Metadata-Version: 2.4
Name: termexec
Version: 0.0.3
Summary: Terminal executor for AI agents, with ANSI escape sequence support and image screenshots
Home-page: https://github.com/james4ever0/termexec
Author: James Brown
Author-email: randomvoidmail@foxmail.com
Classifier: Programming Language :: Python :: 3
Classifier: Operating System :: OS Independent
Requires-Python: >=3.8
License-File: LICENSE
Requires-Dist: agg-python-bindings==0.1.4
Requires-Dist: ptyprocess==0.7.0
Requires-Dist: pydantic
Dynamic: author
Dynamic: author-email
Dynamic: classifier
Dynamic: description
Dynamic: description-content-type
Dynamic: home-page
Dynamic: license-file
Dynamic: requires-dist
Dynamic: requires-python
Dynamic: summary
